[{"path": "/gesiscss/mlkoblenz", "title": "gesiscss/mlkoblenz: Repository for the Machine Learning lecture", "count": 1, "uniques": 1}, {"path": "/gesiscss/mlkoblenz/blob/master/index.html", "title": "mlkoblenz/index.html at master \u00b7 gesiscss/mlkoblenz", "count": 1, "uniques": 1}, {"path": "/gesiscss/mlkoblenz/graphs/traffic", "title": "Traffic \u00b7 gesiscss/mlkoblenz", "count": 1, "uniques": 1}, {"path": "/gesiscss/mlkoblenz/pulse", "title": "Pulse \u00b7 gesiscss/mlkoblenz", "count": 1, "uniques": 1}]